LICENSE
MANIFEST.in
setup.py
mongoSuite/Instance.py
mongoSuite/Node.py
mongoSuite/ReplSet.py
mongoSuite/Tools.py
mongoSuite/__init__.py
mongoSuite.egg-info/PKG-INFO
mongoSuite.egg-info/SOURCES.txt
mongoSuite.egg-info/dependency_links.txt
mongoSuite.egg-info/requires.txt
mongoSuite.egg-info/top_level.txt
scripts/mongoSuite