Metadata-Version: 1.1
Name: mongoSuite
Version: 0.2.1
Summary: Manage multiple instances of MongoDB on multiple hosts with one command line tool
Home-page: https://github.com/william-p/mongoSuite
Author: William Pain
Author-email: wpain@capensis.fr
License: MongoSuite
